equation_sampler/__init__.py
equation_sampler/equation_tree.py
equation_sampler/measure.py
equation_sampler/sampler.py
equation_sampler/data/adjusted_probabilities.json
equation_sampler/util/hashing.py
equation_sampler/util/unary_minus_to_binary.py
equation_sampler-0.0.5.dist-info/METADATA
equation_sampler-0.0.5.dist-info/WHEEL
equation_sampler-0.0.5.dist-info/top_level.txt
equation_sampler-0.0.5.dist-info/RECORD
