Metadata-Version: 2.1
Name: equation-sampler
Version: 0.0.5
Summary: Tool to sample equations
Author-email: Ioana Marinescu <ioanam@princeton.edu>
License: MIT license
Project-URL: homepage, http://www.empiricalresearch.ai
Project-URL: repository, https://github.com/AutoResearch/autora-synthetic-generator-equation-sampler
Project-URL: documentation, https://autoresearch.github.io/autora/
Requires-Python: <4,>=3.8
Requires-Dist: numpy
Requires-Dist: sympy
Requires-Dist: importlib-resources
Provides-Extra: dev
Requires-Dist: autora-core[dev] ; extra == 'dev'
